README.rst
setup.py
parsewiki/__init__.py
parsewiki/page.py
parsewiki.egg-info/PKG-INFO
parsewiki.egg-info/SOURCES.txt
parsewiki.egg-info/dependency_links.txt
parsewiki.egg-info/requires.txt
parsewiki.egg-info/top_level.txt