Metadata-Version: 1.1
Name: parsewiki
Version: 1.0.2
Summary: Wikipedia parser for Python
Home-page: https://github.com/jortdevreeze/ParseWiki
Author: Jort de Vreeze
Author-email: j.devreeze@iwm-tuebingen.de
License: MIT
Keywords: python wikipedia parser API
Platform: UNKNOWN
Classifier: Development Status :: 4 - Beta
Classifier: Topic :: Software Development :: Libraries
Classifier: License :: OSI Approved :: MIT License
Classifier: Programming Language :: Python
Classifier: Programming Language :: Python :: 3
